stonewave/sql/udtfs/__init__.py
stonewave/sql/udtfs/base_dataloader.py
stonewave/sql/udtfs/base_function.py
stonewave/sql/udtfs/constants.py
stonewave/sql/udtfs/function_executor.py
stonewave/sql/udtfs/functions/faker/__init__.py
stonewave/sql/udtfs/functions/faker/info.toml
stonewave/sql/udtfs/functions/generate_union/__init__.py
stonewave/sql/udtfs/functions/generate_union/info.toml
stonewave/sql/udtfs/functions/geo_to_h3/__init__.py
stonewave/sql/udtfs/functions/geo_to_h3/info.toml
stonewave/sql/udtfs/functions/load_excel/__init__.py
stonewave/sql/udtfs/functions/load_excel/info.toml
stonewave/sql/udtfs/functions/parse_binary/__init__.py
stonewave/sql/udtfs/functions/parse_binary/formats/__init__.py
stonewave/sql/udtfs/functions/parse_binary/formats/java_class.ksy
stonewave/sql/udtfs/functions/parse_binary/formats/java_class.py
stonewave/sql/udtfs/functions/parse_binary/formats/png.ksy
stonewave/sql/udtfs/functions/parse_binary/formats/png.py
stonewave/sql/udtfs/functions/parse_binary/info.toml
stonewave/sql/udtfs/functions/parse_format/__init__.py
stonewave/sql/udtfs/functions/parse_format/info.toml
stonewave/sql/udtfs/functions/parse_grok/__init__.py
stonewave/sql/udtfs/functions/parse_grok/info.toml
stonewave/sql/udtfs/functions/parse_sql/__init__.py
stonewave/sql/udtfs/functions/pivot_table/__init__.py
stonewave/sql/udtfs/functions/pivot_table/info.toml
stonewave/sql/udtfs/functions/summarize/__init__.py
stonewave/sql/udtfs/functions/summarize/info.toml
stonewave/sql/udtfs/functions/transpose/__init__.py
stonewave/sql/udtfs/functions/transpose/info.toml
stonewave/sql/udtfs/functions/unpivot_table/__init__.py
stonewave/sql/udtfs/functions/unpivot_table/info.toml
stonewave/sql/udtfs/functions/url/__init__.py
stonewave/sql/udtfs/functions/url/info.toml
stonewave/sql/udtfs/load_function.py
stonewave/sql/udtfs/logger.py
stonewave/sql/udtfs/main.py
stonewave/sql/udtfs/protocol/__init__.py
stonewave/sql/udtfs/protocol/arrow/__init__.py
stonewave_sql_udtfs-0.6.4.dist-info/METADATA
stonewave_sql_udtfs-0.6.4.dist-info/WHEEL
stonewave_sql_udtfs-0.6.4.dist-info/entry_points.txt
stonewave_sql_udtfs-0.6.4.dist-info/RECORD
